sidpy/__init__.py
sidpy/__version__.py
sidpy/base/__init__.py
sidpy/base/dict_utils.py
sidpy/base/num_utils.py
sidpy/base/string_utils.py
sidpy/hdf/__init__.py
sidpy/hdf/dtype_utils.py
sidpy/hdf/hdf_utils.py
sidpy/hdf/prov_utils.py
sidpy/hdf/reg_ref.py
sidpy/io/__init__.py
sidpy/io/interface_utils.py
sidpy/sid/__init__.py
sidpy/sid/dataset.py
sidpy/sid/dimension.py
sidpy/sid/reader.py
sidpy/sid/translator.py
sidpy/viz/__init__.py
sidpy/viz/dataset_viz.py
sidpy/viz/jupyter_utils.py
sidpy/viz/plot_utils/__init__.py
sidpy/viz/plot_utils/cmap.py
sidpy/viz/plot_utils/curve.py
sidpy/viz/plot_utils/image.py
sidpy/viz/plot_utils/misc.py
sidpy_lite-0.12.9.dist-info/licenses/LICENSE
sidpy_lite-0.12.9.dist-info/METADATA
sidpy_lite-0.12.9.dist-info/WHEEL
sidpy_lite-0.12.9.dist-info/top_level.txt
sidpy_lite-0.12.9.dist-info/RECORD
